rocket/__init__.py
rocket/rocket.py
myrocket-1.0.0.dist-info/LICENSE.txt
myrocket-1.0.0.dist-info/METADATA
myrocket-1.0.0.dist-info/WHEEL
myrocket-1.0.0.dist-info/top_level.txt
myrocket-1.0.0.dist-info/RECORD
