Metadata-Version: 2.1
Name: myrocket
Version: 1.0.0
Summary: An awesome package that does something
Home-page: http://pypi.python.org/pypi/myrocket/
Author: Ikram_Dadoune-rocket
Author-email: I.dadoune@esi-sba.dz
License: LICENSE.txt
License-File: LICENSE.txt
